gpx_converter/__init__.py
gpx_converter/base.py
gpx_converter/cli.py
gpx_converter-2.1.0.dist-info/AUTHORS.rst
gpx_converter-2.1.0.dist-info/LICENSE
gpx_converter-2.1.0.dist-info/METADATA
gpx_converter-2.1.0.dist-info/WHEEL
gpx_converter-2.1.0.dist-info/entry_points.txt
gpx_converter-2.1.0.dist-info/top_level.txt
gpx_converter-2.1.0.dist-info/RECORD
