Metadata-Version: 2.1
Name: gpx-converter
Version: 2.1.0
Summary: Python package for manipulating gpx files and easily convert gpx to other different formats.
Home-page: https://github.com/nidhaloff/gpx_converter
Author: Nidhal Baccouri
Author-email: nidhalbacc@gmail.com
License: MIT license
Keywords: gpx_converter,GPX,GPS,GSI,Global Positioning System,Positioning System,Position,GPS conversion,GPX conversion,convert gpx to csv,convert csv to gpx,convert gpx to json,convert gpx to array,convert json to gpx
Classifier: Development Status :: 5 - Production/Stable
Classifier: Intended Audience :: Developers
Classifier: License :: OSI Approved :: MIT License
Classifier: Topic :: Scientific/Engineering :: GIS
Classifier: Topic :: Scientific/Engineering
Classifier: Topic :: Software Development
Classifier: Topic :: Scientific/Engineering :: Physics
Classifier: Topic :: Education
Classifier: Operating System :: OS Independent
Classifier: Natural Language :: English
Classifier: Programming Language :: Python :: 3.6
Classifier: Programming Language :: Python :: 3.7
Classifier: Programming Language :: Python :: 3.8
Requires-Python: >=3.5
License-File: LICENSE
License-File: AUTHORS.rst
Requires-Dist: gpxpy (>=1.4.0)
Requires-Dist: numpy (>=1.18.1)
Requires-Dist: pandas (>=1.0.3)
